graphbin/__init__.py
graphbin/cli.py
graphbin/graphbin_Canu.py
graphbin/graphbin_Flye.py
graphbin/graphbin_Func.py
graphbin/graphbin_MEGAHIT.py
graphbin/graphbin_Miniasm.py
graphbin/graphbin_SGA.py
graphbin/graphbin_SPAdes.py
graphbin/bidirectionalmap/__init__.py
graphbin/bidirectionalmap/bidirectionalmap.py
graphbin/labelpropagation/__init__.py
graphbin/labelpropagation/labelprop.py
graphbin/parsers/__init__.py
graphbin/parsers/canu_parser.py
graphbin/parsers/flye_parser.py
graphbin/parsers/megahit_parser.py
graphbin/parsers/miniasm_parser.py
graphbin/parsers/sga_parser.py
graphbin/parsers/spades_parser.py
graphbin/support/gfa2fasta.py
graphbin/support/prep_result.py
graphbin/support/visualise_result_Flye_Canu_Miniasm.py
graphbin/support/visualise_result_MEGAHIT.py
graphbin/support/visualise_result_SGA.py
graphbin/support/visualise_result_SPAdes.py
graphbin/utils/graphbin_Canu.py
graphbin/utils/graphbin_Flye.py
graphbin/utils/graphbin_Func.py
graphbin/utils/graphbin_MEGAHIT.py
graphbin/utils/graphbin_Miniasm.py
graphbin/utils/graphbin_Options.py
graphbin/utils/graphbin_SGA.py
graphbin/utils/graphbin_SPAdes.py
graphbin/utils/parsers/__init__.py
graphbin/utils/parsers/canu_parser.py
graphbin/utils/parsers/flye_parser.py
graphbin/utils/parsers/megahit_parser.py
graphbin/utils/parsers/miniasm_parser.py
graphbin/utils/parsers/sga_parser.py
graphbin/utils/parsers/spades_parser.py
graphbin-1.7.4.dist-info/entry_points.txt
graphbin-1.7.4.dist-info/LICENSE
graphbin-1.7.4.dist-info/WHEEL
graphbin-1.7.4.dist-info/METADATA
graphbin-1.7.4.dist-info/RECORD
