Metadata-Version: 2.1
Name: graphbin
Version: 1.7.4
Summary: GraphBin: Refined binning of metagenomic contigs using assembly graphs.
Keywords: genomics,bioinformatics
Author-email: Vijini Mallawaarachchi <viji.mallawaarachchi@gmail.com>, Anuradha Wickramarachchi <anuradhawick@gmail.com>, Yu Lin <yu.lin@anu.edu.au>
Requires-Python: >=3.7
Classifier: Development Status :: 5 - Production/Stable
Classifier: Intended Audience :: Science/Research
Classifier: License :: OSI Approved :: BSD License
Classifier: Topic :: Scientific/Engineering :: Bio-Informatics
Classifier: Programming Language :: Python :: 3.7
Classifier: Programming Language :: Python :: 3.8
Classifier: Programming Language :: Python :: 3.9
Classifier: Programming Language :: Python :: 3.10
Requires-Dist: igraph
Requires-Dist: cogent3
Requires-Dist: cairocffi
Requires-Dist: click
Requires-Dist: black ; extra == "dev"
Requires-Dist: click ; extra == "dev"
Requires-Dist: docformatter ; extra == "dev"
Requires-Dist: flit ; extra == "dev"
Requires-Dist: nox ; extra == "dev"
Requires-Dist: isort ; extra == "dev"
Requires-Dist: pytest ; extra == "dev"
Requires-Dist: pytest-cov ; extra == "dev"
Requires-Dist: pytest-xdist ; extra == "dev"
Requires-Dist: nox ; extra == "test"
Requires-Dist: pytest ; extra == "test"
Requires-Dist: pytest-cov ; extra == "test"
Requires-Dist: pytest-xdist ; extra == "test"
Project-URL: Bug Tracker, https://github.com/metagentools/GraphBin/issues
Project-URL: Documentation, https://graphbin.readthedocs.io/en/latest/
Project-URL: Source Code, https://github.com/metagentools/GraphBin/
Provides-Extra: dev
Provides-Extra: test
